<?xml version="1.0" encoding="utf-8"?>
<Dependencies>
  <ProductDependencies>
    <!-- Winforms / WPF -->
    <Dependency Name="Microsoft.WindowsDesktop.App" Version="3.0.0-preview8-28379-02">
      <Uri>https://github.com/dotnet/core-setup</Uri>
      <Sha>3a87ac0079c714f13e35b319ad68cd15f66e0172</Sha>
    </Dependency>
    <Dependency Name="Microsoft.NETCore.App" Version="3.0.0-preview8-28379-02">
      <Uri>https://github.com/dotnet/core-setup</Uri>
      <Sha>3a87ac0079c714f13e35b319ad68cd15f66e0172</Sha>
    </Dependency>
    <Dependency Name="NETStandard.Library.Ref" Version="2.1.0-preview8-28379-02">
      <Uri>https://github.com/dotnet/core-setup</Uri>
      <Sha>3a87ac0079c714f13e35b319ad68cd15f66e0172</Sha>
    </Dependency>
    <Dependency Name="Microsoft.AspNetCore.App.Ref" Version="3.0.0-preview8.19379.2">
      <Uri>https://github.com/aspnet/AspNetCore</Uri>
      <Sha>e0e9096af526448cb1a02f97e60efd8567b7ba35</Sha>
    </Dependency>
    <Dependency Name="Microsoft.AspNetCore.App.Runtime.win-x64" Version="3.0.0-preview8.19379.2">
      <Uri>https://github.com/aspnet/AspNetCore</Uri>
      <Sha>e0e9096af526448cb1a02f97e60efd8567b7ba35</Sha>
    </Dependency>
    <Dependency Name="Microsoft.AspNetCore.DeveloperCertificates.XPlat" Version="3.0.0-preview8.19379.2">
      <Uri>https://github.com/aspnet/AspNetCore</Uri>
      <Sha>e0e9096af526448cb1a02f97e60efd8567b7ba35</Sha>
    </Dependency>
    <Dependency Name="dotnet-dev-certs" Version="3.0.0-preview8.19379.2">
      <Uri>https://github.com/aspnet/AspNetCore</Uri>
      <Sha>e0e9096af526448cb1a02f97e60efd8567b7ba35</Sha>
    </Dependency>
    <Dependency Name="dotnet-user-secrets" Version="3.0.0-preview8.19379.2">
      <Uri>https://github.com/aspnet/AspNetCore</Uri>
      <Sha>e0e9096af526448cb1a02f97e60efd8567b7ba35</Sha>
    </Dependency>
    <Dependency Name="dotnet-watch" Version="3.0.0-preview8.19379.2">
      <Uri>https://github.com/aspnet/AspNetCore</Uri>
      <Sha>e0e9096af526448cb1a02f97e60efd8567b7ba35</Sha>
    </Dependency>
    <Dependency Name="Microsoft.DotNet.Common.ItemTemplates" Version="5.0.0-alpha1.19380.2">
      <Uri>https://github.com/dotnet/templating</Uri>
      <Sha>842077d01eb49047e3b818630ad5d3614d7eddf2</Sha>
    </Dependency>
    <Dependency Name="Microsoft.Dotnet.Toolset.Internal" Version="5.0.100-alpha1.19381.3">
      <Uri>https://github.com/dotnet/toolset</Uri>
      <Sha>c063bf87f4e021a4d9e8a7ba2d3eb3c0415839fd</Sha>
    </Dependency>
    <Dependency Name="Microsoft.NET.Sdk" Version="5.0.100-alpha1.19379.4">
      <Uri>https://github.com/dotnet/sdk</Uri>
      <Sha>39b5747f4a27333e876ce76fcdbb8fd09e3dd875</Sha>
    </Dependency>
    <Dependency Name="Microsoft.DotNet.MSBuildSdkResolver" Version="5.0.100-alpha1.19381.2">
      <Uri>https://github.com/dotnet/cli</Uri>
      <Sha>6396041927bb4fac80b2e0a68df5c2de566daa75</Sha>
    </Dependency>
    <!-- For coherency purposes, these versions should be gated by the versions of winforms and wpf routed via core setup -->
    <Dependency Name="Microsoft.Dotnet.WinForms.ProjectTemplates" Version="4.8.0-preview8.19378.11" CoherentParentDependency="Microsoft.WindowsDesktop.App">
      <Uri>https://github.com/dotnet/winforms</Uri>
      <Sha>6f69e1c0bfa132a3eccd854982b591213ea86044</Sha>
    </Dependency>
    <Dependency Name="Microsoft.DotNet.Wpf.ProjectTemplates" Version="3.0.0-preview8.19378.16" CoherentParentDependency="Microsoft.WindowsDesktop.App">
      <Uri>https://github.com/dotnet/wpf</Uri>
      <Sha>73748bff4a485121754109d9abe1ef1e725b82e1</Sha>
    </Dependency>
  </ProductDependencies>
  <ToolsetDependencies>
    <Dependency Name="Microsoft.DotNet.Arcade.Sdk" Version="1.0.0-beta.19380.3">
      <Uri>https://github.com/dotnet/arcade</Uri>
      <Sha>def377f94747dac91482aad67b33a1c011ffc770</Sha>
    </Dependency>
  </ToolsetDependencies>
</Dependencies>
