<?xml version="1.0" encoding="utf-8"?>
<Dependencies>
  <ProductDependencies>
    <Dependency Name="Microsoft.WindowsDesktop.App.Ref" Version="7.0.7" CoherentParentDependency="Microsoft.NET.Sdk">
      <Uri>https://dev.azure.com/dnceng/internal/_git/dotnet-windowsdesktop</Uri>
      <Sha>eacd999cfa912fdb8ff68aa20fb8f3f8eb1c6170</Sha>
    </Dependency>
    <Dependency Name="VS.Redist.Common.WindowsDesktop.SharedFramework.x64.7.0" Version="7.0.7-servicing.23275.3" CoherentParentDependency="Microsoft.NET.Sdk">
      <Uri>https://dev.azure.com/dnceng/internal/_git/dotnet-windowsdesktop</Uri>
      <Sha>eacd999cfa912fdb8ff68aa20fb8f3f8eb1c6170</Sha>
    </Dependency>
    <Dependency Name="VS.Redist.Common.WindowsDesktop.TargetingPack.x64.7.0" Version="7.0.7-servicing.23275.3" CoherentParentDependency="Microsoft.NET.Sdk">
      <Uri>https://dev.azure.com/dnceng/internal/_git/dotnet-windowsdesktop</Uri>
      <Sha>eacd999cfa912fdb8ff68aa20fb8f3f8eb1c6170</Sha>
    </Dependency>
    <Dependency Name="Microsoft.WindowsDesktop.App.Runtime.win-x64" Version="7.0.7" CoherentParentDependency="Microsoft.NET.Sdk">
      <Uri>https://dev.azure.com/dnceng/internal/_git/dotnet-windowsdesktop</Uri>
      <Sha>eacd999cfa912fdb8ff68aa20fb8f3f8eb1c6170</Sha>
    </Dependency>
    <Dependency Name="VS.Redist.Common.NetCore.SharedFramework.x64.7.0" Version="7.0.7-servicing.23274.4" CoherentParentDependency="Microsoft.NET.Sdk">
      <Uri>https://dev.azure.com/dnceng/internal/_git/dotnet-runtime</Uri>
      <Sha>5b20af47d99620150c53eaf5db8636fdf730b126</Sha>
    </Dependency>
    <Dependency Name="Microsoft.NETCore.App.Ref" Version="7.0.7" CoherentParentDependency="Microsoft.NET.Sdk">
      <Uri>https://dev.azure.com/dnceng/internal/_git/dotnet-runtime</Uri>
      <Sha>5b20af47d99620150c53eaf5db8636fdf730b126</Sha>
    </Dependency>
    <Dependency Name="VS.Redist.Common.NetCore.TargetingPack.x64.7.0" Version="7.0.7-servicing.23274.4" CoherentParentDependency="Microsoft.NET.Sdk">
      <Uri>https://dev.azure.com/dnceng/internal/_git/dotnet-runtime</Uri>
      <Sha>5b20af47d99620150c53eaf5db8636fdf730b126</Sha>
    </Dependency>
    <Dependency Name="Microsoft.NETCore.App.Runtime.win-x64" Version="7.0.7" CoherentParentDependency="Microsoft.NET.Sdk">
      <Uri>https://dev.azure.com/dnceng/internal/_git/dotnet-runtime</Uri>
      <Sha>5b20af47d99620150c53eaf5db8636fdf730b126</Sha>
      <SourceBuildTarball RepoName="runtime" ManagedOnly="true" />
    </Dependency>
    <Dependency Name="Microsoft.NETCore.App.Host.win-x64" Version="7.0.7" CoherentParentDependency="Microsoft.NET.Sdk">
      <Uri>https://dev.azure.com/dnceng/internal/_git/dotnet-runtime</Uri>
      <Sha>5b20af47d99620150c53eaf5db8636fdf730b126</Sha>
    </Dependency>
    <Dependency Name="Microsoft.NETCore.DotNetHostResolver" Version="7.0.7" CoherentParentDependency="Microsoft.NET.Sdk">
      <Uri>https://dev.azure.com/dnceng/internal/_git/dotnet-runtime</Uri>
      <Sha>5b20af47d99620150c53eaf5db8636fdf730b126</Sha>
    </Dependency>
    <!-- Change blob version in GenerateLayout.targets if this is unpinned to service targeting pack -->
    <!-- No new netstandard.library planned for 3.1 timeframe at this time. -->
    <Dependency Name="NETStandard.Library.Ref" Version="2.1.0" Pinned="true">
      <Uri>https://github.com/dotnet/core-setup</Uri>
      <Sha>7d57652f33493fa022125b7f63aad0d70c52d810</Sha>
    </Dependency>
    <Dependency Name="Microsoft.NETCore.Platforms" Version="7.0.3" CoherentParentDependency="Microsoft.NET.Sdk">
      <Uri>https://dev.azure.com/dnceng/internal/_git/dotnet-runtime</Uri>
      <Sha>5b20af47d99620150c53eaf5db8636fdf730b126</Sha>
    </Dependency>
    <Dependency Name="Microsoft.AspNetCore.App.Ref" Version="7.0.7" CoherentParentDependency="Microsoft.NET.Sdk">
      <Uri>https://dev.azure.com/dnceng/internal/_git/dotnet-aspnetcore</Uri>
      <Sha>3dfc6fda80a10797b8c8fda1970e7b377fd8ed8d</Sha>
    </Dependency>
    <Dependency Name="Microsoft.AspNetCore.App.Ref.Internal" Version="7.0.7-servicing.23274.8" CoherentParentDependency="Microsoft.NET.Sdk">
      <Uri>https://dev.azure.com/dnceng/internal/_git/dotnet-aspnetcore</Uri>
      <Sha>3dfc6fda80a10797b8c8fda1970e7b377fd8ed8d</Sha>
      <SourceBuild RepoName="aspnetcore" ManagedOnly="true" />
    </Dependency>
    <Dependency Name="Microsoft.AspNetCore.App.Runtime.win-x64" Version="7.0.7" CoherentParentDependency="Microsoft.NET.Sdk">
      <Uri>https://dev.azure.com/dnceng/internal/_git/dotnet-aspnetcore</Uri>
      <Sha>3dfc6fda80a10797b8c8fda1970e7b377fd8ed8d</Sha>
    </Dependency>
    <Dependency Name="VS.Redist.Common.AspNetCore.SharedFramework.x64.7.0" Version="7.0.7-servicing.23274.8" CoherentParentDependency="Microsoft.NET.Sdk">
      <Uri>https://dev.azure.com/dnceng/internal/_git/dotnet-aspnetcore</Uri>
      <Sha>3dfc6fda80a10797b8c8fda1970e7b377fd8ed8d</Sha>
    </Dependency>
    <Dependency Name="dotnet-dev-certs" Version="7.0.7-servicing.23274.8" CoherentParentDependency="Microsoft.NET.Sdk">
      <Uri>https://dev.azure.com/dnceng/internal/_git/dotnet-aspnetcore</Uri>
      <Sha>3dfc6fda80a10797b8c8fda1970e7b377fd8ed8d</Sha>
    </Dependency>
    <Dependency Name="dotnet-user-jwts" Version="7.0.7-servicing.23274.8" CoherentParentDependency="Microsoft.NET.Sdk">
      <Uri>https://dev.azure.com/dnceng/internal/_git/dotnet-aspnetcore</Uri>
      <Sha>3dfc6fda80a10797b8c8fda1970e7b377fd8ed8d</Sha>
    </Dependency>
    <Dependency Name="dotnet-user-secrets" Version="7.0.7-servicing.23274.8" CoherentParentDependency="Microsoft.NET.Sdk">
      <Uri>https://dev.azure.com/dnceng/internal/_git/dotnet-aspnetcore</Uri>
      <Sha>3dfc6fda80a10797b8c8fda1970e7b377fd8ed8d</Sha>
    </Dependency>
    <Dependency Name="Microsoft.DotNet.Test.ProjectTemplates.2.1" Version="1.0.2-beta4.22406.1">
      <Uri>https://github.com/dotnet/test-templates</Uri>
      <Sha>0385265f4d0b6413d64aea0223172366a9b9858c</Sha>
    </Dependency>
    <Dependency Name="Microsoft.DotNet.Test.ProjectTemplates.5.0" Version="1.1.0-rc.23305.2">
      <Uri>https://github.com/dotnet/test-templates</Uri>
      <Sha>98b55256c6cdfc0ed98c52d7d39127fa55971330</Sha>
    </Dependency>
    <Dependency Name="Microsoft.DotNet.Test.ProjectTemplates.6.0" Version="1.1.0-rc.23305.2">
      <Uri>https://github.com/dotnet/test-templates</Uri>
      <Sha>98b55256c6cdfc0ed98c52d7d39127fa55971330</Sha>
    </Dependency>
    <Dependency Name="Microsoft.DotNet.Test.ProjectTemplates.7.0" Version="1.1.0-rc.23305.2">
      <Uri>https://github.com/dotnet/test-templates</Uri>
      <Sha>98b55256c6cdfc0ed98c52d7d39127fa55971330</Sha>
      <SourceBuild RepoName="test-templates" ManagedOnly="true" />
    </Dependency>
    <Dependency Name="Microsoft.DotNet.Common.ItemTemplates" Version="7.0.400-preview.23313.39">
      <Uri>https://github.com/dotnet/sdk</Uri>
      <Sha>0c315a2c61c52bf2804ab5b5c28d3289c24cd588</Sha>
    </Dependency>
    <Dependency Name="Microsoft.TemplateEngine.Cli" Version="7.0.400-preview.23313.39">
      <Uri>https://github.com/dotnet/sdk</Uri>
      <Sha>0c315a2c61c52bf2804ab5b5c28d3289c24cd588</Sha>
    </Dependency>
    <Dependency Name="Microsoft.NET.Sdk" Version="7.0.400-preview.23313.39">
      <Uri>https://github.com/dotnet/sdk</Uri>
      <Sha>0c315a2c61c52bf2804ab5b5c28d3289c24cd588</Sha>
      <SourceBuild RepoName="sdk" ManagedOnly="true" />
    </Dependency>
    <Dependency Name="Microsoft.DotNet.MSBuildSdkResolver" Version="7.0.400-preview.23313.39">
      <Uri>https://github.com/dotnet/sdk</Uri>
      <Sha>0c315a2c61c52bf2804ab5b5c28d3289c24cd588</Sha>
    </Dependency>
    <!-- For coherency purposes, these versions should be gated by the versions of winforms and wpf routed via windowsdesktop -->
    <Dependency Name="Microsoft.Dotnet.WinForms.ProjectTemplates" Version="7.0.7-servicing.23274.5" CoherentParentDependency="Microsoft.WindowsDesktop.App.Runtime.win-x64">
      <Uri>https://dev.azure.com/dnceng/internal/_git/dotnet-winforms</Uri>
      <Sha>b4a5f0c6839363dea534f21736a9d0726c14b41c</Sha>
    </Dependency>
    <Dependency Name="Microsoft.DotNet.Wpf.ProjectTemplates" Version="7.0.7-servicing.23274.5" CoherentParentDependency="Microsoft.WindowsDesktop.App.Runtime.win-x64">
      <Uri>https://dev.azure.com/dnceng/internal/_git/dotnet-wpf</Uri>
      <Sha>512eac4b458953da405f51ec0ae7766bcb7b32e5</Sha>
    </Dependency>
    <Dependency Name="Microsoft.FSharp.Compiler" Version="12.7.0-beta.23313.7" CoherentParentDependency="Microsoft.NET.Sdk">
      <Uri>https://github.com/dotnet/fsharp</Uri>
      <Sha>fbab5feade1e7426dc715b772ea59a287adf2165</Sha>
    </Dependency>
    <Dependency Name="Microsoft.SourceBuild.Intermediate.fsharp" Version="7.0.400-beta.23313.7" CoherentParentDependency="Microsoft.NET.Sdk">
      <Uri>https://github.com/dotnet/fsharp</Uri>
      <Sha>fbab5feade1e7426dc715b772ea59a287adf2165</Sha>
      <SourceBuild RepoName="fsharp" ManagedOnly="true" />
    </Dependency>
    <Dependency Name="Microsoft.NET.Test.Sdk" Version="17.7.0-preview-23313-04" CoherentParentDependency="Microsoft.NET.Sdk">
      <Uri>https://github.com/microsoft/vstest</Uri>
      <Sha>a006b59a7af55448b69ea835f0037437f363c25f</Sha>
      <SourceBuild RepoName="vstest" ManagedOnly="true" />
    </Dependency>
    <Dependency Name="Microsoft.NET.ILLink.Tasks" Version="7.0.100-1.23211.1" CoherentParentDependency="Microsoft.NET.Sdk">
      <Uri>https://github.com/dotnet/linker</Uri>
      <Sha>9d4b3f3e0c100fe5ac4dc7f40d14d792178dbd0c</Sha>
      <SourceBuild RepoName="linker" ManagedOnly="true" />
      <RepoName>linker</RepoName>
    </Dependency>
    <Dependency Name="Microsoft.Net.Compilers.Toolset" Version="4.7.0-3.23312.16" CoherentParentDependency="Microsoft.NET.Sdk">
      <Uri>https://github.com/dotnet/roslyn</Uri>
      <Sha>f93b9a42ff7b6e92ff5d0d9d3d70f466ca3ed450</Sha>
      <SourceBuild RepoName="roslyn" ManagedOnly="true" />
    </Dependency>
    <Dependency Name="Microsoft.Build" Version="17.7.0-preview-23312-02" CoherentParentDependency="Microsoft.NET.Sdk">
      <Uri>https://github.com/dotnet/msbuild</Uri>
      <Sha>df97a4b69224643b4af407f41b33f8c9762af3c0</Sha>
    </Dependency>
    <Dependency Name="Microsoft.SourceBuild.Intermediate.msbuild" Version="17.7.0-preview-23312-02" CoherentParentDependency="Microsoft.NET.Sdk">
      <Uri>https://github.com/dotnet/msbuild</Uri>
      <Sha>df97a4b69224643b4af407f41b33f8c9762af3c0</Sha>
      <SourceBuild RepoName="msbuild" ManagedOnly="true" />
    </Dependency>
    <Dependency Name="NuGet.Build.Tasks" Version="6.7.0-preview.3.71" CoherentParentDependency="Microsoft.NET.Sdk">
      <Uri>https://github.com/nuget/nuget.client</Uri>
      <Sha>566ced13280613f419b8b057583c0dd8f6ced724</Sha>
      <SourceBuildTarball RepoName="nuget-client" ManagedOnly="true" />
    </Dependency>
    <Dependency Name="Microsoft.ApplicationInsights" Version="2.0.0">
      <Uri>https://github.com/Microsoft/ApplicationInsights-dotnet</Uri>
      <Sha>53b80940842204f78708a538628288ff5d741a1d</Sha>
    </Dependency>
    <Dependency Name="Microsoft.NET.Workload.Emscripten.net6.Manifest-7.0.100" Version="7.0.7" CoherentParentDependency="VS.Redist.Common.NetCore.SharedFramework.x64.7.0">
      <Uri>https://github.com/dotnet/emsdk</Uri>
      <Sha>b3cf128502f8fc7f9f9212a4dfaff67a2bce7bda</Sha>
    </Dependency>
    <Dependency Name="Microsoft.NET.Workload.Emscripten.net7.Manifest-7.0.100" Version="7.0.7" CoherentParentDependency="VS.Redist.Common.NetCore.SharedFramework.x64.7.0">
      <Uri>https://github.com/dotnet/emsdk</Uri>
      <Sha>b3cf128502f8fc7f9f9212a4dfaff67a2bce7bda</Sha>
    </Dependency>
    <Dependency Name="Microsoft.Deployment.DotNet.Releases" Version="1.0.0-preview5.1.22263.1">
      <Uri>https://github.com/dotnet/deployment-tools</Uri>
      <Sha>c3ad00ae84489071080a606f6a8e43c9a91a5cc2</Sha>
      <SourceBuildTarball RepoName="deployment-tools" ManagedOnly="true" />
    </Dependency>
    <Dependency Name="Microsoft.SourceBuild.Intermediate.source-build-externals" Version="7.0.0-alpha.1.22505.1">
      <Uri>https://github.com/dotnet/source-build-externals</Uri>
      <Sha>c47ba6c19d50081f90008da8bc61b3ac20348f20</Sha>
      <SourceBuild RepoName="source-build-externals" ManagedOnly="true" />
    </Dependency>
    <Dependency Name="Microsoft.SourceBuild.Intermediate.symreader" Version="1.4.0-beta2-21475-02">
      <Uri>https://github.com/dotnet/symreader</Uri>
      <Sha>7b9791daa3a3477eb22ec805946c9fff8b42d8ca</Sha>
      <SourceBuild RepoName="symreader" ManagedOnly="true" />
    </Dependency>
  </ProductDependencies>
  <ToolsetDependencies>
    <Dependency Name="Microsoft.DotNet.Arcade.Sdk" Version="7.0.0-beta.23281.4">
      <Uri>https://github.com/dotnet/arcade</Uri>
      <Sha>6a71ed4ba6a70e66abe9f9bdc4009fa1de35132f</Sha>
      <SourceBuild RepoName="arcade" ManagedOnly="true" />
    </Dependency>
    <Dependency Name="Microsoft.DotNet.CMake.Sdk" Version="7.0.0-beta.23281.4">
      <Uri>https://github.com/dotnet/arcade</Uri>
      <Sha>6a71ed4ba6a70e66abe9f9bdc4009fa1de35132f</Sha>
    </Dependency>
    <Dependency Name="Microsoft.DotNet.Build.Tasks.Installers" Version="7.0.0-beta.23281.4">
      <Uri>https://github.com/dotnet/arcade</Uri>
      <Sha>6a71ed4ba6a70e66abe9f9bdc4009fa1de35132f</Sha>
    </Dependency>
    <Dependency Name="Microsoft.SourceBuild.Intermediate.source-build-reference-packages" Version="7.0.0-alpha.1.23219.1">
      <Uri>https://github.com/dotnet/source-build-reference-packages</Uri>
      <Sha>525b6c35cc5c5c9b80b47044be2e4e77858d505a</Sha>
      <SourceBuild RepoName="source-build-reference-packages" ManagedOnly="true" />
    </Dependency>
    <Dependency Name="Microsoft.SourceLink.GitHub" Version="1.2.0-beta-22429-01" CoherentParentDependency="Microsoft.DotNet.Arcade.Sdk">
      <Uri>https://github.com/dotnet/sourcelink</Uri>
      <Sha>e57efa1ed395dd6975b33052719facb24f03ee0b</Sha>
      <SourceBuild RepoName="sourcelink" ManagedOnly="true" />
    </Dependency>
    <Dependency Name="Microsoft.DotNet.XliffTasks" Version="1.0.0-beta.22427.1" CoherentParentDependency="Microsoft.DotNet.Arcade.Sdk">
      <Uri>https://github.com/dotnet/xliff-tasks</Uri>
      <Sha>740189d758fb3bbdc118c5b6171ef1a7351a8c44</Sha>
      <SourceBuild RepoName="xliff-tasks" ManagedOnly="true" />
    </Dependency>
  </ToolsetDependencies>
</Dependencies>
